Workbook
Name Slicer_Department: #N/A
Name Slicer_Transaction_Month: #N/A

Sheet Clean Financial Data
A1: Transaction ID | B1: Transaction Date | C1: Transaction Type | D1: Department | E1: Category | F1: Business Segment | G1: Location | H1: Vendor | I1: Payment Method | J1: Budget Amount | K1: Actual Amount | L1: Variance | M1: Variance % | N1: Budget Status | O1: Net Amount | P1: Transaction Month
A2: FIN-00001 | B2: 45688 | C2: Expense | D2: Finance | E2: Equipment & Maintenance | F2: Services | G2: Faisalabad | H2: Softworks | I2: Cash | J2: 6208 | K2: 795.11 | L2: =K2-J2 -> -5412.89 | M2: =IF(J2=0,0,L2/J2) -> -0.87192171 | N2: =IF(J2=0,"No Budget",IF(K2>J2,"Over Budget",IF(K2<J2,"Under Budget","On Budget"))) -> Under Budget | O2: =IF(C2="Revenue",K2,-K2) -> -795.11 | P2: =DATE(YEAR(B2),MONTH(B2),1) -> 45658
A3: FIN-00002 | B3: 45690 | C3: Expense | D3: Administration | E3: Office Supplies | F3: Corporate | G3: Lahore | H3: Officepro | I3: Bank Transfer | J3: 3000 | K3: 1176.76 | L3: =K3-J3 -> -1823.24 | M3: =IF(J3=0,0,L3/J3) -> -0.60774667 | N3: =IF(J3=0,"No Budget",IF(K3>J3,"Over Budget",IF(K3<J3,"Under Budget","On Budget"))) -> Under Budget | O3: =IF(C3="Revenue",K3,-K3) -> -1176.76 | P3: =DATE(YEAR(B3),MONTH(B3),1) -> 45689
A4: FIN-00003 | B4: 45731 | C4: Revenue | D4: Operations | E4: Subscription Revenue | F4: Wholesale | G4: Peshawar | H4: Shipfast | I4: Online Payment | J4: 4850 | K4: 6088.89 | L4: =K4-J4 -> 1238.89 | M4: =IF(J4=0,0,L4/J4) -> 0.25544124 | N4: =IF(J4=0,"No Budget",IF(K4>J4,"Over Budget",IF(K4<J4,"Under Budget","On Budget"))) -> Over Budget | O4: =IF(C4="Revenue",K4,-K4) -> 6088.89 | P4: =DATE(YEAR(B4),MONTH(B4),1) -> 45717
A5: FIN-00004 | B5: 45767 | C5: Revenue | D5: Sales | E5: Product Sales | F5: Online | G5: Faisalabad | H5: Softworks | I5: Online Payment | J5: 11547.62 | K5: 4195.52 | L5: =K5-J5 -> -7352.1 | M5: =IF(J5=0,0,L5/J5) -> -0.63667665 | N5: =IF(J5=0,"No Budget",IF(K5>J5,"Over Budget",IF(K5<J5,"Under Budget","On Budget"))) -> Under Budget | O5: =IF(C5="Revenue",K5,-K5) -> 4195.52 | P5: =DATE(YEAR(B5),MONTH(B5),1) -> 45748
A6: FIN-00005 | B6: 45782 | C6: Expense | D6: Marketing | E6: Travel & Transport | F6: Online | G6: Karachi | H6: Powergrid | I6: Debit Card | J6: 4666.67 | K6: 524.33 | L6: =K6-J6 -> -4142.34 | M6: =IF(J6=0,0,L6/J6) -> -0.88764365 | N6: =IF(J6=0,"No Budget",IF(K6>J6,"Over Budget",IF(K6<J6,"Under Budget","On Budget"))) -> Under Budget | O6: =IF(C6="Revenue",K6,-K6) -> -524.33 | P6: =DATE(YEAR(B6),MONTH(B6),1) -> 45778
A7: FIN-00006 | B7: 45814 | C7: Expense | D7: Operations | E7: Rent & Facilities | F7: Corporate | G7: Karachi | H7: Buildcare | I7: Bank Transfer | J7: 6500 | K7: 10406.47 | L7: =K7-J7 -> 3906.47 | M7: =IF(J7=0,0,L7/J7) -> 0.60099538 | N7: =IF(J7=0,"No Budget",IF(K7>J7,"Over Budget",IF(K7<J7,"Under Budget","On Budget"))) -> Over Budget | O7: =IF(C7="Revenue",K7,-K7) -> -10406.47 | P7: =DATE(YEAR(B7),MONTH(B7),1) -> 45809
A8: FIN-00007 | B8: 45855 | C8: Revenue | D8: Sales | E8: Product Sales | F8: Online | G8: Islamabad | H8: Markethub | I8: Cash | J8: 9615.38 | K8: 19758.34 | L8: =K8-J8 -> 10142.96 | M8: =IF(J8=0,0,L8/J8) -> 1.0548683 | N8: =IF(J8=0,"No Budget",IF(K8>J8,"Over Budget",IF(K8<J8,"Under Budget","On Budget"))) -> Over Budget | O8: =IF(C8="Revenue",K8,-K8) -> 19758.34 | P8: =DATE(YEAR(B8),MONTH(B8),1) -> 45839
A9: FIN-00008 | B9: 45887 | C9: Expense | D9: Marketing | E9: Salaries & Benefits | F9: Online | G9: Lahore | H9: Buildcare | I9: Cash | J9: 7826.09 | K9: 12296.53 | L9: =K9-J9 -> 4470.44 | M9: =IF(J9=0,0,L9/J9) -> 0.57122267 | N9: =IF(J9=0,"No Budget",IF(K9>J9,"Over Budget",IF(K9<J9,"Under Budget","On Budget"))) -> Over Budget | O9: =IF(C9="Revenue",K9,-K9) -> -12296.53 | P9: =DATE(YEAR(B9),MONTH(B9),1) -> 45870
A10: FIN-00009 | B10: 45909 | C10: Expense | D10: Operations | E10: Software & Subscriptions | F10: Wholesale | G10: Karachi | H10: Peoplefirst | I10: Credit Card | J10: 7350 | K10: 251.01 | L10: =K10-J10 -> -7098.99 | M10: =IF(J10=0,0,L10/J10) -> -0.96584898 | N10: =IF(J10=0,"No Budget",IF(K10>J10,"Over Budget",IF(K10<J10,"Under Budget","On Budget"))) -> Under Budget | O10: =IF(C10="Revenue",K10,-K10) -> -251.01 | P10: =DATE(YEAR(B10),MONTH(B10),1) -> 45901
A11: FIN-00010 | B11: 45940 | C11: Revenue | D11: Sales | E11: Product Sales | F11: Online | G11: Lahore | H11: Unknown | I11: Cash | J11: 10000 | K11: 7622.41 | L11: =K11-J11 -> -2377.59 | M11: =IF(J11=0,0,L11/J11) -> -0.237759 | N11: =IF(J11=0,"No Budget",IF(K11>J11,"Over Budget",IF(K11<J11,"Under Budget","On Budget"))) -> Under Budget | O11: =IF(C11="Revenue",K11,-K11) -> 7622.41 | P11: =DATE(YEAR(B11),MONTH(B11),1) -> 45931
A12: FIN-00011 | B12: 45982 | C12: Expense | D12: Marketing | E12: Professional Services | F12: Retail | G12: Islamabad | H12: Peoplefirst | I12: Credit Card | J12: 6000 | K12: 0 | L12: =K12-J12 -> -6000 | M12: =IF(J12=0,0,L12/J12) -> -1 | N12: =IF(J12=0,"No Budget",IF(K12>J12,"Over Budget",IF(K12<J12,"Under Budget","On Budget"))) -> Under Budget | O12: =IF(C12="Revenue",K12,-K12) -> 0 | P12: =DATE(YEAR(B12),MONTH(B12),1) -> 45962
A13: FIN-00012 | B13: 46003 | C13: Expense | D13: Finance | E13: Salaries & Benefits | F13: Wholesale | G13: Karachi | H13: Adsphere | I13: Debit Card | J13: 6715.38 | K13: 8473.89 | L13: =K13-J13 -> 1758.51 | M13: =IF(J13=0,0,L13/J13) -> 0.26186307 | N13: =IF(J13=0,"No Budget",IF(K13>J13,"Over Budget",IF(K13<J13,"Under Budget","On Budget"))) -> Over Budget | O13: =IF(C13="Revenue",K13,-K13) -> -8473.89 | P13: =DATE(YEAR(B13),MONTH(B13),1) -> 45992
... A2501: FIN-02500 | B2501: 46179 | C2501: Revenue | D2501: Finance | E2501: Subscription Revenue | F2501: Corporate | G2501: Islamabad | H2501: Markethub | I2501: Bank Transfer | J2501: 7272.73 | K2501: 4270.84 | L2501: =K2501-J2501 -> -3001.89 | M2501: =IF(J2501=0,0,L2501/J2501) -> -0.41275972 | N2501: =IF(J2501=0,"No Budget",IF(K2501>J2501,"Over Budget",IF(K2501<J2501,"Under Budget","On Budget"))) -> Under Budget | O2501: =IF(C2501="Revenue",K2501,-K2501) -> 4270.84 | P2501: =DATE(YEAR(B2501),MONTH(B2501),1) -> 46174

Sheet Dashboard

Sheet PivotTables
B2: Sum of Budget Amount | C2: Sum of Actual Amount | D2: Sum of Net Amount | E2: Count of Transaction ID | H2: Column Labels | M2: Column Labels
B3: 17105049 | C3: 16270075 | D3: 128460.79 | E3: 2500 | H3: Expense | I3: Revenue | J3: Grand Total | M3: No Budget | N3: Over Budget | O3: Under Budget | P3: Grand Total
G4: Sum of Actual Amount | H4: 8070807 | I4: 8199267.8 | J4: 16270075 | L4: Sum of Actual Amount | M4: 47976.8 | N4: 11251288 | O4: 4970810.3 | P4: 16270075
B5: =GETPIVOTDATA("Sum of Budget Amount",$B$2) -> 17105049 | C5: =GETPIVOTDATA("Sum of Actual Amount",$B$2) -> 16270075 | D5: =GETPIVOTDATA("Sum of Net Amount",$B$2) -> 128460.79 | E5: =GETPIVOTDATA("Count of Transaction ID",$B$2) -> 2500 | H5: =GETPIVOTDATA("Actual Amount",$G$2,"Transaction Type","Expense") -> 8070807 | I5: =GETPIVOTDATA("Actual Amount",$G$2,"Transaction Type","Revenue") -> 8199267.8 | N5: =GETPIVOTDATA("Actual Amount",$L$2,"Budget Status","Over Budget") -> 11251288 | O5: =GETPIVOTDATA("Actual Amount",$L$2,"Budget Status","Under Budget") -> 4970810.3
B8: Revenue vs Expense By Months | G8: Expense By Category | J8: Actual vs Budget by Department | N8: Revenue by Category
B10: Sum of Actual Amount | C10: Column Labels | G10: Transaction Type | H10: Expense | J10: Row Labels | K10: Total Budget | L10: Total Actual | N10: Transaction Type | O10: Revenue
B11: Row Labels | C11: Expense | D11: Revenue | E11: Grand Total | J11: Administration | K11: 3177655.4 | L11: 2915637.4
B12: 45658 | C12: 380927.93 | D12: 452540.9 | E12: 833468.83 | G12: Row Labels | H12: Sum of Actual Amount | J12: Finance | K12: 1614121.8 | L12: 1651336.7 | N12: Row Labels | O12: Sum of Actual Amount
B13: 45689 | C13: 317275.15 | D13: 381240.21 | E13: 698515.36 | G13: Equipment & Maintenance | H13: 477055.22 | J13: Hr | K13: 1343816.8 | L13: 1287839.7 | N13: Other Income | O13: 158500.96
B14: 45717 | C14: 556502.55 | D14: 523874.29 | E14: 1080376.8 | G14: Logistics & Shipping | H14: 438157.08 | J14: It | K14: 1728839.4 | L14: 1639522.8 | N14: Product Sales | O14: 5220984.9
B15: 45748 | C15: 412382.95 | D15: 423830.03 | E15: 836212.98 | G15: Marketing & Advertising | H15: 902483.53 | J15: Marketing | K15: 2025390.1 | L15: 1906195.5 | N15: Service Revenue | O15: 2096558
B16: 45778 | C16: 546445.01 | D16: 442479.99 | E16: 988925 | G16: Office Supplies | H16: 126273.25 | J16: Operations | K16: 2704810.9 | L16: 2406070.6 | N16: Subscription Revenue | O16: 694391.2
B17: 45809 | C17: 504257.99 | D17: 554136.87 | E17: 1058394.9 | G17: Professional Services | H17: 528165.1 | J17: Sales | K17: 4406754.8 | L17: 4397099.8 | N17: Unknown | O17: 28832.68
B18: 45839 | C18: 481565.85 | D18: 456473.56 | E18: 938039.41 | G18: Rent & Facilities | H18: 1213123.8 | J18: Unknown | K18: 103660.02 | L18: 66372.25 | N18: Grand Total | O18: 8199267.8
B19: 45870 | C19: 482726.06 | D19: 548921.02 | E19: 1031647.1 | G19: Salaries & Benefits | H19: 3622899.4 | J19: Grand Total | K19: 17105049 | L19: 16270075
B20: 45901 | C20: 457402.62 | D20: 407520.85 | E20: 864923.47 | G20: Software & Subscriptions | H20: 332678.11
B21: 45931 | C21: 465193.97 | D21: 528056.56 | E21: 993250.53 | G21: Travel & Transport | H21: 163874.05
B22: 45962 | C22: 341734.93 | D22: 439282.52 | E22: 781017.45 | G22: Unknown | H22: 25734.77
B23: 45992 | C23: 524745.13 | D23: 324008.17 | E23: 848753.3 | G23: Utilities | H23: 240362.71
B24: 46023 | C24: 449674.44 | D24: 429940.71 | E24: 879615.15 | G24: Grand Total | H24: 8070807
B25: 46174 | C25: 454373.53 | D25: 519930.91 | E25: 974304.44
B26: 46082 | C26: 498461.23 | D26: 348012.62 | E26: 846473.85
B27: 46113 | C27: 372966.76 | D27: 552049.66 | E27: 925016.42 | G27: Net Amount by Business Segment | J27: Budget Status | N27: Amount by Payment Method
B28: 46143 | C28: 334593.06 | D28: 456510.74 | E28: 791103.8
B29: 46054 | C29: 489577.84 | D29: 410458.18 | E29: 900036.02 | G29: Row Labels | H29: Sum of Net Amount | J29: Row Labels | K29: Sum of Actual Amount | N29: Row Labels | O29: Sum of Actual Amount
B30: Grand Total | C30: 8070807 | D30: 8199267.8 | E30: 16270075 | G30: Corporate | H30: -208742.39 | J30: No Budget | K30: 47976.8 | N30: Bank Transfer | O30: 4676303.3
G31: Online | H31: 389949.95 | J31: Over Budget | K31: 11251288 | N31: Cash | O31: 1220285.8
G32: Retail | H32: -99270.02 | J32: Under Budget | K32: 4970810.3 | N32: Credit Card | O32: 3933305.2
G33: Services | H33: 122072.5 | J33: Grand Total | K33: 16270075 | N33: Debit Card | O33: 2903783.7
G34: Wholesale | H34: -75549.25 | N34: Online Payment | O34: 3386231.4
B35: Revenue by Business Segment | G35: Grand Total | H35: 128460.79 | N35: Unknown | O35: 150165.34
N36: Grand Total | O36: 16270075
B37: Transaction Type | C37: Revenue
B39: Row Labels | C39: Sum of Actual Amount
B40: Corporate | C40: 1031045.4
B41: Online | C41: 2243719.6
B42: Retail | C42: 2257926.2
B43: Services | C43: 1241254.3
B44: Wholesale | C44: 1425322.3
B45: Grand Total | C45: 8199267.8

Sheet KPI Summary
A1: KPI | B1: Value
A2: Total Transactions | B2: =COUNTA('Clean Financial Data'!A2:A2501) -> 2500
A3: Total Budget | B3: =SUM('Clean Financial Data'!J2:J2501) -> 17105049
A4: Total Actual | B4: =SUM('Clean Financial Data'!K2:K2501) -> 16270075
A5: Total Revenue | B5: =SUMIFS('Clean Financial Data'!K2:K2501,'Clean Financial Data'!C2:C2501,"Revenue") -> 8199267.8
A6: Total Expenses | B6: =SUMIFS('Clean Financial Data'!K2:K2501,'Clean Financial Data'!C2:C2501,"Expense") -> 8070807
A7: Net Amount | B7: =SUM('Clean Financial Data'!O2:O2501) -> 128460.79
A8: Over Budget Amount | B8: =SUMIFS('Clean Financial Data'!K2:K2501,'Clean Financial Data'!N2:N2501,"Over Budget") -> 11251288
A9: Under Budget Amount | B9: =SUMIFS('Clean Financial Data'!K2:K2501,'Clean Financial Data'!N2:N2501,"Under Budget") -> 4970810.3

Sheet Data Quality Plan
B2: Issue | C2: Count | D2: Recommended Action | E2: Reason
B3: Exact duplicate rows | C3: 30 | D3: Remove duplicates | E3: Duplicate transaction records
B4: Missing Department | C4: 15 | D4: Recover / validate | E4: Required for departmental analysis
B5: Missing Vendor | C5: 12 | D5: Recover / standardize | E5: Required for vendor analysis
B6: Missing Payment Method | C6: 18 | D6: Standardize / use Unknown if unrecoverable | E6: Payment analysis field
B7: Missing Category | C7: 10 | D7: Recover using transaction type / mapping | E7: Required for category analysis
B8: Inconsistent text / capitalization | C8: 17 | D8: Standardize text | E8: Consistent PivotTable grouping
B9: Mixed date formats | C9: 12 | D9: Convert to real Excel dates | E9: Consistent time analysis
B10: Blank Budget Amount | C10: 8 | D10: Recover from category/month budget logic | E10: Budget variance analysis
B11: Missing Actual Amount | C11: 6 | D11: Flag/remove | E11: Actual amount is required
B12: Zero Actual Amount | C12: 4 | D12: Flag/remove | E12: No financial activity
